cge_modeling/__init__.py
cge_modeling/_version.py
cge_modeling/optimize.py
cge_modeling/plotting.py
cge_modeling/production_functions.py
cge_modeling/base/__init__.py
cge_modeling/base/build.py
cge_modeling/base/cge.py
cge_modeling/base/function_wrappers.py
cge_modeling/base/primitives.py
cge_modeling/base/utilities.py
cge_modeling/compile/__init__.py
cge_modeling/compile/constants.py
cge_modeling/compile/euler.py
cge_modeling/compile/jax.py
cge_modeling/compile/numba.py
cge_modeling/compile/numba_tools.py
cge_modeling/compile/pytensor.py
cge_modeling/compile/pytensor_tools.py
cge_modeling/compile/sympy.py
cge_modeling/compile/sympytensor.py
cge_modeling/tools/__init__.py
cge_modeling/tools/output_tools.py
cge_modeling/tools/parsing.py
cge_modeling/tools/rebalance.py
cge_modeling/tools/sympy_tools.py
cge_modeling/tools/utils.py
cge_modeling-0.0.6.dist-info/METADATA
cge_modeling-0.0.6.dist-info/WHEEL
cge_modeling-0.0.6.dist-info/top_level.txt
cge_modeling-0.0.6.dist-info/RECORD
