Metadata-Version: 2.1
Name: cge-modeling
Version: 0.0.6
Summary: Computable general equlibrium models and policy simulation via autodiff with Pytensor
Author-email: Jesse Grabowski <jessegrabowski@gmail.com>
Keywords: computable general equlibrium,partial general equlibrium,economics,macroeconomics,numerical,simulation,autodiff
Classifier: Development Status :: 2 - Pre-Alpha
Classifier: Intended Audience :: Science/Research
Classifier: Programming Language :: Python
Classifier: Topic :: Scientific/Engineering
Classifier: Operating System :: Microsoft :: Windows
Classifier: Operating System :: POSIX
Classifier: Operating System :: Unix
Classifier: Operating System :: MacOS
Classifier: Programming Language :: Python :: 3
Classifier: Programming Language :: Python :: 3.10
Classifier: Programming Language :: Python :: 3.11
Classifier: Programming Language :: Python :: 3.12
Requires-Python: <3.13,>=3.10
Requires-Dist: setuptools
Requires-Dist: numba
Requires-Dist: numpy<2
Requires-Dist: sympy<1.13
Requires-Dist: scipy<1.14
Requires-Dist: pandas
Requires-Dist: joblib
Requires-Dist: pytensor
Requires-Dist: latextable
Requires-Dist: texttable
Requires-Dist: sympytensor
Requires-Dist: xarray
Requires-Dist: arviz
Requires-Dist: fastprogress
Requires-Dist: numba-progress
Requires-Dist: matplotlib
Requires-Dist: better-optimize
Provides-Extra: dev
Requires-Dist: pre-commit; extra == "dev"
Requires-Dist: pytest; extra == "dev"
Requires-Dist: pytest-cov; extra == "dev"
Requires-Dist: versioneer; extra == "dev"
Provides-Extra: docs
Requires-Dist: ipython; extra == "docs"
Requires-Dist: jupyter-sphinx; extra == "docs"
Requires-Dist: myst-nb; extra == "docs"
Requires-Dist: numpydoc; extra == "docs"
Requires-Dist: pre-commit; extra == "docs"
Requires-Dist: sphinx>=5; extra == "docs"
Requires-Dist: sphinx-copybutton; extra == "docs"
Requires-Dist: sphinx-design; extra == "docs"
Requires-Dist: sphinx-notfound-page; extra == "docs"
Requires-Dist: sphinx-sitemap; extra == "docs"
Requires-Dist: sphinx-codeautolink; extra == "docs"
Requires-Dist: sphinxcontrib-bibtex; extra == "docs"
Requires-Dist: pydata-sphinx-theme; extra == "docs"
Requires-Dist: watermark; extra == "docs"
